university/__init__.py
university/admin.py
university/apps.py
university/models.py
university/tests.py
university/views.py
citrinedjangomodule-1.0.dist-info/METADATA
citrinedjangomodule-1.0.dist-info/WHEEL
citrinedjangomodule-1.0.dist-info/top_level.txt
citrinedjangomodule-1.0.dist-info/RECORD
