Metadata-Version: 2.1
Name: citrinedjangomodule
Version: 1.0
Summary: citrinedjangomodule
Author: Farah Ben Mohamed
Author-email: farahbenmohamed.carnelian@gmail.com
Requires-Dist: Django ==3.2.12
Requires-Dist: python-decouple ==3.4
Requires-Dist: amqp ==5.1.1
Requires-Dist: asgiref ==3.5.2
Requires-Dist: async-timeout ==4.0.2
Requires-Dist: auditlog3 ==1.0.1
Requires-Dist: billiard ==3.6.4.0
Requires-Dist: celery ==5.2.7
Requires-Dist: certifi ==2021.10.8
Requires-Dist: charset-normalizer ==2.0.10
Requires-Dist: click ==8.1.3
Requires-Dist: click-didyoumean ==0.3.0
Requires-Dist: click-plugins ==1.1.1
Requires-Dist: click-repl ==0.2.0
Requires-Dist: configparser ==5.0.2
Requires-Dist: defusedxml ==0.7.1
Requires-Dist: Deprecated ==1.2.13
Requires-Dist: diff-match-patch ==20200713
Requires-Dist: dj-database-url ==0.5.0
Requires-Dist: django-cors-headers ==3.7.0
Requires-Dist: django-environ ==0.9.0
Requires-Dist: django-field-history ==0.8.0
Requires-Dist: django-import-export ==3.0.1
Requires-Dist: django-jsonfield ==1.4.1
Requires-Dist: django-robots ==4.0
Requires-Dist: django-simple-history ==3.1.1
Requires-Dist: django-tables2 ==2.4.1
Requires-Dist: djangorestframework ==3.12.2
Requires-Dist: environ ==1.0
Requires-Dist: et-xmlfile ==1.1.0
Requires-Dist: ez-setup ==0.9
Requires-Dist: Jinja2 ==3.0.3
Requires-Dist: kombu ==5.2.4
Requires-Dist: MarkupPy ==1.14
Requires-Dist: MarkupSafe ==2.0.1
Requires-Dist: numpy ==1.23.4
Requires-Dist: odfpy ==1.4.1
Requires-Dist: openpyxl ==3.0.10
Requires-Dist: packaging ==21.3
Requires-Dist: pandas ==1.5.1
Requires-Dist: Pillow ==8.2.0
Requires-Dist: prompt-toolkit ==3.0.31
Requires-Dist: psycopg2 ==2.8.6
Requires-Dist: psycopg2-binary ==2.9.5
Requires-Dist: PyJWT ==2.1.0
Requires-Dist: pyparsing ==3.0.9
Requires-Dist: python-dateutil ==2.8.2
Requires-Dist: pytz ==2022.5
Requires-Dist: PyYAML ==6.0
Requires-Dist: redis ==4.3.4
Requires-Dist: requests ==2.26.0
Requires-Dist: rules ==3.3
Requires-Dist: six ==1.15.0
Requires-Dist: sqlparse ==0.4.1
Requires-Dist: tablib ==3.2.1
Requires-Dist: typing-extensions ==3.10.0.0
Requires-Dist: urllib3 ==1.26.12
Requires-Dist: vine ==5.0.0
Requires-Dist: wcwidth ==0.2.5
Requires-Dist: wrapt ==1.14.1
Requires-Dist: xlrd ==2.0.1
Requires-Dist: xlwt ==1.3.0
Requires-Dist: xmltodict ==0.13.0
Requires-Dist: celery
Requires-Dist: django-import-export
Requires-Dist: django-simple-history
Requires-Dist: django-jsonfield
Requires-Dist: django ==3.2.12
Requires-Dist: django-field-history
Requires-Dist: django-pandas
Requires-Dist: django-tables2
Requires-Dist: xmltodict
Requires-Dist: python-decouple
Requires-Dist: psycopg2
